covbayesvar/__init__.py
covbayesvar/large_bvar.py
covbayesvar/unit_tests.py
covbayesvar-0.2.0.dist-info/METADATA
covbayesvar-0.2.0.dist-info/WHEEL
covbayesvar-0.2.0.dist-info/top_level.txt
covbayesvar-0.2.0.dist-info/RECORD
