Metadata-Version: 2.2
Name: covbayesvar
Version: 0.2.0
Summary: This package has functions to estimate large BVAR models with COVID volatility, plot conditional and unconditional forecasts, scenario analyses, generalized impulse response functions, joint distribution of forecasts and visualize structural breaks using the methods established in Giannone et al. (2015), Banbura et. al (2015), Lenza and Primiceri (2022), and Crump et. al (2021).
Author: Sudiksha Joshi
Author-email: joshi27s@uw.edu
Classifier: Programming Language :: Python :: 3
Requires-Python: >=3.8
Requires-Dist: numpy
Requires-Dist: pandas
Requires-Dist: scipy
Requires-Dist: matplotlib
Dynamic: author
Dynamic: author-email
Dynamic: classifier
Dynamic: description
Dynamic: description-content-type
Dynamic: requires-dist
Dynamic: requires-python
Dynamic: summary
